SeeThru_Feeds/__init__.py
SeeThru_Feeds/Core/ConfigParser.py
SeeThru_Feeds/Core/SeeThruFeed.py
SeeThru_Feeds/Core/__init__.py
SeeThru_Feeds/Core/Config/ApiKey.py
SeeThru_Feeds/Core/Config/Feed.py
SeeThru_Feeds/Core/Config/Header.py
SeeThru_Feeds/Core/Config/__init__.py
SeeThru_Feeds/Core/Config/Script/Meta.py
SeeThru_Feeds/Core/Config/Script/State.py
SeeThru_Feeds/Core/Config/Script/__init__.py
SeeThru_Feeds/Core/Exceptions/Config.py
SeeThru_Feeds/Core/templates/Manage_Template.template
SeeThru_Feeds/Core/templates/Script_Template.template
SeeThru_Feeds/Library/__init__.py
SeeThru_Feeds/Library/Components/Database.py
SeeThru_Feeds/Library/Components/HTTP.py
SeeThru_Feeds/Library/Components/SNMP.py
SeeThru_Feeds/Library/Components/Socket.py
SeeThru_Feeds/Library/Components/Zabbix.py
SeeThru_Feeds/Library/Components/__init__.py
SeeThru_Feeds/Library/Scripts/StatusPage.py
SeeThru_Feeds/Library/Scripts/TCPPortOpen.py
SeeThru_Feeds/Library/Scripts/UDPPortOpen.py
SeeThru_Feeds/Model/Attribution.py
SeeThru_Feeds/Model/__init__.py
SeeThru_Feeds/Model/Components/ComponentBase.py
SeeThru_Feeds/Model/Components/__init__.py
SeeThru_Feeds/Model/Feeds/Feed.py
SeeThru_Feeds/Model/Feeds/__init__.py
SeeThru_Feeds/Model/Properties/Exceptions.py
SeeThru_Feeds/Model/Properties/Properties.py
SeeThru_Feeds/Model/Properties/PropertyManager.py
SeeThru_Feeds/Model/Properties/__init__.py
SeeThru_Feeds/Model/Scripts/ScriptBase.py
SeeThru_Feeds/Model/Scripts/ScriptResult.py
SeeThru_Feeds/Model/Scripts/ScriptState.py
SeeThru_Feeds/Model/Scripts/__init__.py
tests/__init__.py
tests/test_Core_ConfigParser.py
tests/test_SeeThru_Feed.py
SeeThru_Feeds-0.0.2.dist-info/LICENSE
SeeThru_Feeds-0.0.2.dist-info/METADATA
SeeThru_Feeds-0.0.2.dist-info/WHEEL
SeeThru_Feeds-0.0.2.dist-info/entry_points.txt
SeeThru_Feeds-0.0.2.dist-info/top_level.txt
SeeThru_Feeds-0.0.2.dist-info/RECORD
